torchrun_jsc/__init__.py
torchrun_jsc/__main__.py
torchrun_jsc/hostname_utils.py
torchrun_jsc/parsing.py
torchrun_jsc/run.py
torchrun_jsc/run_old.py
torchrun_jsc/patching/__init__.py
torchrun_jsc/patching/arg_patching.py
torchrun_jsc/patching/matches_machine_hostname_patching.py
torchrun_jsc/patching/node_desc_generator_patching.py
torchrun_jsc/patching/rendezvous_store_info_patching.py
torchrun_jsc/patching/simple_elastic_agent_patching.py
torchrun_jsc-0.0.18.dist-info/licenses/LICENSE
torchrun_jsc-0.0.18.dist-info/METADATA
torchrun_jsc-0.0.18.dist-info/WHEEL
torchrun_jsc-0.0.18.dist-info/entry_points.txt
torchrun_jsc-0.0.18.dist-info/top_level.txt
torchrun_jsc-0.0.18.dist-info/RECORD
